{
  "name": "Default Bot",
  "core": {
    "name": "transformer",
    "intents": {
      "Hi": "hello",
      "Hello": "hello",
      "Hello, world": "hello",
      "hi there": "hello",
      "Hackernews": "hn",
      "Hacker news": "hn",
      "What is on Hackernews today?": "hn",
      "Shout": "shout",
      "Can you shout?": "shout",
      "Bye": "bye",
      "ciao": "bye",
      "bye bye": "bye",
      "see you": "bye"
    }
  },
  "actions": [
    {
      "name": "Shout",
      "settings": {
      },
      "active": {
        "intents": ["shout"]
      }
    },
    {
      "name": "Talk",
      "settings": {
      },
      "active": {
        "intents": ["bye", "hello"]
      }
    },
    {
      "name": "Hackernews - Top Story",
      "settings": {
      },
      "active": {
        "intents": ["hn"]
      }
    }
  ]
}
